{
  "displayFieldName": "EVENTSTATUS",
  "fieldAliases": {
    "OBJECTID": "OBJECTID",
    "BEGINTIME": "BEGINTIME",
    "ESTIMATEDTIMERESTORATION": "ESTIMATEDTIMERESTORATION",
    "CUSTOMERSOUT": "CUSTOMERSOUT",
    "EVENTSTATUS": "EVENTSTATUS",
    "TIMESTAMP": "TIMESTAMP",
    "BATCHID": "BATCHID",
    "COMMUNITIES": "COMMUNITIES",
    "STATES": "STATES",
    "CREWSTATUS": "CREWSTATUS"
  },
  "geometryType": "esriGeometryPoint",
  "spatialReference": {
    "wkid": 102100,
    "latestWkid": 3857
  },
  "fields": [
    {
      "name": "OBJECTID",
      "type": "esriFieldTypeOID",
      "alias": "OBJECTID"
    },
    {
      "name": "BEGINTIME",
      "type": "esriFieldTypeDate",
      "alias": "BEGINTIME",
      "length": 8
    },
    {
      "name": "ESTIMATEDTIMERESTORATION",
      "type": "esriFieldTypeDate",
      "alias": "ESTIMATEDTIMERESTORATION",
      "length": 8
    },
    {
      "name": "CUSTOMERSOUT",
      "type": "esriFieldTypeSmallInteger",
      "alias": "CUSTOMERSOUT"
    },
    {
      "name": "EVENTSTATUS",
      "type": "esriFieldTypeString",
      "alias": "EVENTSTATUS",
      "length": 255
    },
    {
      "name": "TIMESTAMP",
      "type": "esriFieldTypeDate",
      "alias": "TIMESTAMP",
      "length": 8
    },
    {
      "name": "BATCHID",
      "type": "esriFieldTypeInteger",
      "alias": "BATCHID"
    },
    {
      "name": "COMMUNITIES",
      "type": "esriFieldTypeString",
      "alias": "COMMUNITIES",
      "length": 100
    },
    {
      "name": "STATES",
      "type": "esriFieldTypeString",
      "alias": "STATES",
      "length": 50
    },
    {
      "name": "CREWSTATUS",
      "type": "esriFieldTypeString",
      "alias": "CREWSTATUS",
      "length": 255
    }
  ],
  "features": [
    {
      "attributes": {
        "OBJECTID": 43,
        "BEGINTIME": 1741853520000,
        "ESTIMATEDTIMERESTORATION": 1741860900000,
        "CUSTOMERSOUT": 5,
        "EVENTSTATUS": "Crews are working to restore power as quickly and safely as possible. Please continue to check back for estimated restoration time updates. Thank you for your patience.",
        "TIMESTAMP": null,
        "BATCHID": 13092229,
        "COMMUNITIES": "Golden",
        "STATES": "CO",
        "CREWSTATUS": null
      },
      "geometry": {
        "x": -11713480.396,
        "y": 4830120.3542999998
      }
    },
    {
      "attributes": {
        "OBJECTID": 44,
        "BEGINTIME": 1741854180000,
        "ESTIMATEDTIMERESTORATION": 1741858200000,
        "CUSTOMERSOUT": 10,
        "EVENTSTATUS": "Crews are working to restore power as quickly and safely as possible. Please continue to check back for estimated restoration time updates. Thank you for your patience.",
        "TIMESTAMP": null,
        "BATCHID": 13092229,
        "COMMUNITIES": "Grand Junction",
        "STATES": "CO",
        "CREWSTATUS": null
      },
      "geometry": {
        "x": -12093050.2665,
        "y": 4733816.1384999976
      }
    },
    {
      "attributes": {
        "OBJECTID": 45,
        "BEGINTIME": 1741856580000,
        "ESTIMATEDTIMERESTORATION": 1741860900000,
        "CUSTOMERSOUT": 2,
        "EVENTSTATUS": "Crews are working to restore power as quickly and safely as possible. Please continue to check back for estimated restoration time updates. Thank you for your patience.",
        "TIMESTAMP": null,
        "BATCHID": 13092229,
        "COMMUNITIES": "Gilcrest",
        "STATES": "CO",
        "CREWSTATUS": null
      },
      "geometry": {
        "x": -11664588.924699999,
        "y": 4907982.5864999965
      }
    },
    {
      "attributes": {
        "OBJECTID": 46,
        "BEGINTIME": 1741772220000,
        "ESTIMATEDTIMERESTORATION": 1741879800000,
        "CUSTOMERSOUT": 1,
        "EVENTSTATUS": "Crews are working to restore power as quickly and safely as possible. Please continue to check back for estimated restoration time updates. Thank you for your patience.",
        "TIMESTAMP": null,
        "BATCHID": 13092229,
        "COMMUNITIES": "Arvada",
        "STATES": "CO",
        "CREWSTATUS": null
      },
      "geometry": {
        "x": -11713709.351300001,
        "y": 4841195.7265999988
      }
    },
    {
      "attributes": {
        "OBJECTID": 49,
        "BEGINTIME": 1741851000000,
        "ESTIMATEDTIMERESTORATION": 1741878000000,
        "CUSTOMERSOUT": 7,
        "EVENTSTATUS": "Crews are working to restore power as quickly and safely as possible. Please continue to check back for estimated restoration time updates. Thank you for your patience.",
        "TIMESTAMP": null,
        "BATCHID": 13092229,
        "COMMUNITIES": "Littleton",
        "STATES": "CO",
        "CREWSTATUS": null
      },
      "geometry": {
        "x": -11696300.018199999,
        "y": 4802919.6361000016
      }
    },
    {
      "attributes": {
        "OBJECTID": 50,
        "BEGINTIME": 1741852260000,
        "ESTIMATEDTIMERESTORATION": 1741856400000,
        "CUSTOMERSOUT": 3,
        "EVENTSTATUS": "Crews are working to restore power as quickly and safely as possible. Please continue to check back for estimated restoration time updates. Thank you for your patience.",
        "TIMESTAMP": null,
        "BATCHID": 13092229,
        "COMMUNITIES": "Grand Junction",
        "STATES": "CO",
        "CREWSTATUS": null
      },
      "geometry": {
        "x": -12091769.2908,
        "y": 4732747.0243000016
      }
    },
    {
      "attributes": {
        "OBJECTID": 51,
        "BEGINTIME": 1741853100000,
        "ESTIMATEDTIMERESTORATION": 1741861800000,
        "CUSTOMERSOUT": 45,
        "EVENTSTATUS": "Crews are working to restore power as quickly and safely as possible. Please continue to check back for estimated restoration time updates. Thank you for your patience.",
        "TIMESTAMP": null,
        "BATCHID": 13092229,
        "COMMUNITIES": "Golden",
        "STATES": "CO",
        "CREWSTATUS": null
      },
      "geometry": {
        "x": -11708453.698800001,
        "y": 4825497.7810000032
      }
    },
    {
      "attributes": {
        "OBJECTID": 52,
        "BEGINTIME": 1741855440000,
        "ESTIMATEDTIMERESTORATION": 1741862700000,
        "CUSTOMERSOUT": 1,
        "EVENTSTATUS": "Crews are working to restore power as quickly and safely as possible. Please continue to check back for estimated restoration time updates. Thank you for your patience.",
        "TIMESTAMP": null,
        "BATCHID": 13092229,
        "COMMUNITIES": "Englewood",
        "STATES": "CO",
        "CREWSTATUS": null
      },
      "geometry": {
        "x": -11686117.6589,
        "y": 4815272.0628999993
      }
    },
    {
      "attributes": {
        "OBJECTID": 53,
        "BEGINTIME": 1741856160000,
        "ESTIMATEDTIMERESTORATION": 1741861800000,
        "CUSTOMERSOUT": 7,
        "EVENTSTATUS": "Crews are working to restore power as quickly and safely as possible. Please continue to check back for estimated restoration time updates. Thank you for your patience.",
        "TIMESTAMP": null,
        "BATCHID": 13092229,
        "COMMUNITIES": "Evergreen",
        "STATES": "CO",
        "CREWSTATUS": null
      },
      "geometry": {
        "x": -11724343.135600001,
        "y": 4813414.3924999982
      }
    },
    {
      "attributes": {
        "OBJECTID": 54,
        "BEGINTIME": 1741854360000,
        "ESTIMATEDTIMERESTORATION": 1741861800000,
        "CUSTOMERSOUT": 1,
        "EVENTSTATUS": "The outage has been reported. Please continue to check back for additional updates regarding the restoration progress.",
        "TIMESTAMP": null,
        "BATCHID": 13092229,
        "COMMUNITIES": "Littleton",
        "STATES": "CO",
        "CREWSTATUS": null
      },
      "geometry": {
        "x": -11691632.2239,
        "y": 4805148.8958000019
      }
    },
    {
      "attributes": {
        "OBJECTID": 55,
        "BEGINTIME": 1741855380000,
        "ESTIMATEDTIMERESTORATION": 1741862700000,
        "CUSTOMERSOUT": 2,
        "EVENTSTATUS": "The outage has been reported. Please continue to check back for additional updates regarding the restoration progress.",
        "TIMESTAMP": null,
        "BATCHID": 13092229,
        "COMMUNITIES": "Boulder",
        "STATES": "CO",
        "CREWSTATUS": null
      },
      "geometry": {
        "x": -11733947.855900001,
        "y": 4875192.3915999979
      }
    },
    {
      "attributes": {
        "OBJECTID": 56,
        "BEGINTIME": 1741855620000,
        "ESTIMATEDTIMERESTORATION": 1741862700000,
        "CUSTOMERSOUT": 1,
        "EVENTSTATUS": "Crews are working to restore power as quickly and safely as possible. Please continue to check back for estimated restoration time updates. Thank you for your patience.",
        "TIMESTAMP": null,
        "BATCHID": 13092229,
        "COMMUNITIES": "Morrison",
        "STATES": "CO",
        "CREWSTATUS": null
      },
      "geometry": {
        "x": -11706029.486400001,
        "y": 4811626.3849999979
      }
    },
    {
      "attributes": {
        "OBJECTID": 57,
        "BEGINTIME": 1741855860000,
        "ESTIMATEDTIMERESTORATION": 1741862700000,
        "CUSTOMERSOUT": 1,
        "EVENTSTATUS": "Crews are working to restore power as quickly and safely as possible. Please continue to check back for estimated restoration time updates. Thank you for your patience.",
        "TIMESTAMP": null,
        "BATCHID": 13092229,
        "COMMUNITIES": "Boulder",
        "STATES": "CO",
        "CREWSTATUS": null
      },
      "geometry": {
        "x": -11735204.7732,
        "y": 4871413.1507999972
      }
    },
    {
      "attributes": {
        "OBJECTID": 58,
        "BEGINTIME": 1741856040000,
        "ESTIMATEDTIMERESTORATION": 1741866300000,
        "CUSTOMERSOUT": 1,
        "EVENTSTATUS": "The outage has been reported. Please continue to check back for additional updates regarding the restoration progress.",
        "TIMESTAMP": null,
        "BATCHID": 13092229,
        "COMMUNITIES": "Jamestown",
        "STATES": "CO",
        "CREWSTATUS": null
      },
      "geometry": {
        "x": -11731574.832699999,
        "y": 4882762.2533999979
      }
    },
    {
      "attributes": {
        "OBJECTID": 60,
        "BEGINTIME": 1741853520000,
        "ESTIMATEDTIMERESTORATION": 1741860900000,
        "CUSTOMERSOUT": 19,
        "EVENTSTATUS": "Crews are working to restore power as quickly and safely as possible. Please continue to check back for estimated restoration time updates. Thank you for your patience.",
        "TIMESTAMP": null,
        "BATCHID": 13092229,
        "COMMUNITIES": "Golden",
        "STATES": "CO",
        "CREWSTATUS": null
      },
      "geometry": {
        "x": -11713526.7962,
        "y": 4830087.6639999971
      }
    },
    {
      "attributes": {
        "OBJECTID": 61,
        "BEGINTIME": 1741854960000,
        "ESTIMATEDTIMERESTORATION": null,
        "CUSTOMERSOUT": 21,
        "EVENTSTATUS": "Crews are working to restore power as quickly and safely as possible. Please continue to check back for estimated restoration time updates. Thank you for your patience.",
        "TIMESTAMP": null,
        "BATCHID": 13092229,
        "COMMUNITIES": "Boulder",
        "STATES": "CO",
        "CREWSTATUS": null
      },
      "geometry": {
        "x": -11733068.929499999,
        "y": 4875421.2150000036
      }
    },
    {
      "attributes": {
        "OBJECTID": 62,
        "BEGINTIME": 1741855020000,
        "ESTIMATEDTIMERESTORATION": 1741861800000,
        "CUSTOMERSOUT": 2,
        "EVENTSTATUS": "Crews are working to restore power as quickly and safely as possible. Please continue to check back for estimated restoration time updates. Thank you for your patience.",
        "TIMESTAMP": null,
        "BATCHID": 13092229,
        "COMMUNITIES": "Morrison",
        "STATES": "CO",
        "CREWSTATUS": null
      },
      "geometry": {
        "x": -11708956.3564,
        "y": 4817134.7219000012
      }
    },
    {
      "attributes": {
        "OBJECTID": 63,
        "BEGINTIME": 1741855920000,
        "ESTIMATEDTIMERESTORATION": 1741866300000,
        "CUSTOMERSOUT": 1,
        "EVENTSTATUS": "The outage has been reported. Please continue to check back for additional updates regarding the restoration progress.",
        "TIMESTAMP": null,
        "BATCHID": 13092229,
        "COMMUNITIES": "Broomfield",
        "STATES": "CO",
        "CREWSTATUS": null
      },
      "geometry": {
        "x": -11699307.370999999,
        "y": 4855670.4060999975
      }
    },
    {
      "attributes": {
        "OBJECTID": 64,
        "BEGINTIME": 1741856100000,
        "ESTIMATEDTIMERESTORATION": 1741860900000,
        "CUSTOMERSOUT": 1,
        "EVENTSTATUS": "The outage has been reported. Please continue to check back for additional updates regarding the restoration progress.",
        "TIMESTAMP": null,
        "BATCHID": 13092229,
        "COMMUNITIES": "Brush",
        "STATES": "CO",
        "CREWSTATUS": null
      },
      "geometry": {
        "x": -11535904.867900001,
        "y": 4903355.9614000022
      }
    },
    {
      "attributes": {
        "OBJECTID": 65,
        "BEGINTIME": 1741856100000,
        "ESTIMATEDTIMERESTORATION": 1741866300000,
        "CUSTOMERSOUT": 1,
        "EVENTSTATUS": "The outage has been reported. Please continue to check back for additional updates regarding the restoration progress.",
        "TIMESTAMP": null,
        "BATCHID": 13092229,
        "COMMUNITIES": "Jamestown",
        "STATES": "CO",
        "CREWSTATUS": null
      },
      "geometry": {
        "x": -11731424.092700001,
        "y": 4882607.8038000017
      }
    },
    {
      "attributes": {
        "OBJECTID": 66,
        "BEGINTIME": 1741857240000,
        "ESTIMATEDTIMERESTORATION": 1741861800000,
        "CUSTOMERSOUT": 1,
        "EVENTSTATUS": "Crews are working to restore power as quickly and safely as possible. Please continue to check back for estimated restoration time updates. Thank you for your patience.",
        "TIMESTAMP": null,
        "BATCHID": 13092229,
        "COMMUNITIES": "Fairplay",
        "STATES": "CO",
        "CREWSTATUS": null
      },
      "geometry": {
        "x": -11808671.0919,
        "y": 4754496.9503000006
      }
    },
    {
      "attributes": {
        "OBJECTID": 67,
        "BEGINTIME": 1741857420000,
        "ESTIMATEDTIMERESTORATION": 1741869000000,
        "CUSTOMERSOUT": 1,
        "EVENTSTATUS": "The outage has been reported. Please continue to check back for additional updates regarding the restoration progress.",
        "TIMESTAMP": null,
        "BATCHID": 13092229,
        "COMMUNITIES": "Thornton",
        "STATES": "CO",
        "CREWSTATUS": null
      },
      "geometry": {
        "x": -11684176.637699999,
        "y": 4846507.8774999976
      }
    },
    {
      "attributes": {
        "OBJECTID": 68,
        "BEGINTIME": 1741857360000,
        "ESTIMATEDTIMERESTORATION": 1741869000000,
        "CUSTOMERSOUT": 1,
        "EVENTSTATUS": "The outage has been reported. Please continue to check back for additional updates regarding the restoration progress.",
        "TIMESTAMP": null,
        "BATCHID": 13092229,
        "COMMUNITIES": "Denver",
        "STATES": "CO",
        "CREWSTATUS": null
      },
      "geometry": {
        "x": -11679337.226599999,
        "y": 4827166.6517999992
      }
    },
    {
      "attributes": {
        "OBJECTID": 69,
        "BEGINTIME": 1741857060000,
        "ESTIMATEDTIMERESTORATION": 1741868100000,
        "CUSTOMERSOUT": 1,
        "EVENTSTATUS": "The outage has been reported. Please continue to check back for additional updates regarding the restoration progress.",
        "TIMESTAMP": null,
        "BATCHID": 13092229,
        "COMMUNITIES": "Denver",
        "STATES": "CO",
        "CREWSTATUS": null
      },
      "geometry": {
        "x": -11664374.6669,
        "y": 4838259.8445999995
      }
    }
  ]
}
