[
  {
    "attributes": {
      "objectid": 82930,
      "boundary": null,
      "comments": "The outage has been reported. Please continue to check back for additional updates regarding the restoration progress.",
      "customers": 75,
      "off_": 1770975360000,
      "etr": 1770984900000,
      "ticket": "13095516",
      "outageimpact": "Small",
      "outagetype": "Unplanned Outage",
      "medialink": null,
      "outagestatus": 0,
      "datastatus": null,
      "latlong": "4833764.764799997,-11700448.7609",
      "states": "CO",
      "crewstatus": null,
      "globalid": "{6D276F5F-C200-4E46-B388-B9C88978E1C4}",
      "county": "JEFFERSON",
      "cause": "Outage",
      "city": "Wheat Ridge",
      "xcelarea": "Wheat Ridge"
    },
    "geometry": {
      "x": -11700448.7609,
      "y": 4833764.7647999972
    }
  },
  {
    "attributes": {
      "objectid": 82857,
      "boundary": null,
      "comments": "Crews are working to restore power as quickly and safely as possible. Please continue to check back for estimated restoration time updates. Thank you for your patience.",
      "customers": 79,
      "off_": 1770971820000,
      "etr": 1770981300000,
      "ticket": "13095516",
      "outageimpact": "Small",
      "outagetype": "Unplanned Outage",
      "medialink": null,
      "outagestatus": 0,
      "datastatus": null,
      "latlong": "4829326.9921,-11702249.9548",
      "states": "CO",
      "crewstatus": null,
      "globalid": "{04ECE7E6-34C6-4B1B-8988-DC134C305FD9}",
      "county": "JEFFERSON",
      "cause": "Outage",
      "city": "Lakewood",
      "xcelarea": "Lakewood"
    },
    "geometry": {
      "x": -11702249.9548,
      "y": 4829326.9921000004
    }
  },
  {
    "attributes": {
      "objectid": 82889,
      "boundary": null,
      "comments": "Crews are working to restore power as quickly and safely as possible. Please continue to check back for estimated restoration time updates. Thank you for your patience.",
      "customers": 10,
      "off_": 1770973500000,
      "etr": 1771002900000,
      "ticket": "13095516",
      "outageimpact": "Small",
      "outagetype": "Unplanned Outage",
      "medialink": null,
      "outagestatus": 0,
      "datastatus": null,
      "latlong": "4926752.0380000025,-11656422.9498",
      "states": "CO",
      "crewstatus": null,
      "globalid": "{AF8906E8-BD02-4F73-AAE4-08CF7A51ACF4}",
      "county": "WELD",
      "cause": "Outage",
      "city": "Greeley",
      "xcelarea": "Greeley"
    },
    "geometry": {
      "x": -11656422.9498,
      "y": 4926752.0380000025
    }
  },
  {
    "attributes": {
      "objectid": 82794,
      "boundary": null,
      "comments": "Crews are working to restore power as quickly and safely as possible. Please continue to check back for estimated restoration time updates. Thank you for your patience.",
      "customers": 2,
      "off_": 1770967020000,
      "etr": 1770975000000,
      "ticket": "13095516",
      "outageimpact": "Small",
      "outagetype": "Unplanned Outage",
      "medialink": null,
      "outagestatus": 0,
      "datastatus": null,
      "latlong": "4495868.9212,-11724498.569899999",
      "states": "CO",
      "crewstatus": null,
      "globalid": "{87E0EB2A-7992-43A0-A123-01DEE7BC48A6}",
      "county": "COSTILLA",
      "cause": "Outage",
      "city": "Fort Garland",
      "xcelarea": "Fort Garland"
    },
    "geometry": {
      "x": -11724498.569899999,
      "y": 4495868.9211999997
    }
  },
  {
    "attributes": {
      "objectid": 82856,
      "boundary": null,
      "comments": "Crews are working to restore power as quickly and safely as possible. Please continue to check back for estimated restoration time updates. Thank you for your patience.",
      "customers": 36,
      "off_": 1770971760000,
      "etr": 1771008300000,
      "ticket": "13095516",
      "outageimpact": "Small",
      "outagetype": "Unplanned Outage",
      "medialink": null,
      "outagestatus": 0,
      "datastatus": null,
      "latlong": "4863851.777900003,-11715752.5827",
      "states": "CO",
      "crewstatus": null,
      "globalid": "{4267A0A0-A6C0-4A5C-91DB-3BFB3DC85FF9}",
      "county": "BOULDER",
      "cause": "Outage",
      "city": "Boulder",
      "xcelarea": "Boulder"
    },
    "geometry": {
      "x": -11715752.582699999,
      "y": 4863851.7779000029
    }
  },
  {
    "attributes": {
      "objectid": 82821,
      "boundary": null,
      "comments": "Crews are working to restore power as quickly and safely as possible. Please continue to check back for estimated restoration time updates. Thank you for your patience.",
      "customers": 1,
      "off_": 1770970020000,
      "etr": 1770990300000,
      "ticket": "13095516",
      "outageimpact": "Small",
      "outagetype": "Unplanned Outage",
      "medialink": null,
      "outagestatus": 0,
      "datastatus": null,
      "latlong": "4811078.152500004,-11971862.8116",
      "states": "CO",
      "crewstatus": null,
      "globalid": "{3389625B-422A-48F2-A496-B1D821EA5DAE}",
      "county": "GARFIELD",
      "cause": "Outage",
      "city": "New Castle",
      "xcelarea": "New Castle"
    },
    "geometry": {
      "x": -11971862.8116,
      "y": 4811078.1525000036
    }
  },
  {
    "attributes": {
      "objectid": 82806,
      "boundary": null,
      "comments": "Crews are working to restore power as quickly and safely as possible. Please continue to check back for estimated restoration time updates. Thank you for your patience.",
      "customers": 2,
      "off_": 1770968880000,
      "etr": 1770991200000,
      "ticket": "13095516",
      "outageimpact": "Small",
      "outagetype": "Unplanned Outage",
      "medialink": null,
      "outagestatus": 0,
      "datastatus": null,
      "latlong": "4809475.686300002,-11723146.1127",
      "states": "CO",
      "crewstatus": null,
      "globalid": "{36EB3113-702E-4E2C-AF3A-F62E99910E58}",
      "county": "JEFFERSON",
      "cause": "Outage",
      "city": "Evergreen",
      "xcelarea": "Evergreen"
    },
    "geometry": {
      "x": -11723146.1127,
      "y": 4809475.686300002
    }
  },
  {
    "attributes": {
      "objectid": 82829,
      "boundary": null,
      "comments": "Crews are working to restore power as quickly and safely as possible. Please continue to check back for estimated restoration time updates. Thank you for your patience.",
      "customers": 2,
      "off_": 1770970620000,
      "etr": 1770984000000,
      "ticket": "13095516",
      "outageimpact": "Small",
      "outagetype": "Unplanned Outage",
      "medialink": null,
      "outagestatus": 0,
      "datastatus": null,
      "latlong": "4821866.0744,-11690273.817699999",
      "states": "CO",
      "crewstatus": null,
      "globalid": "{C3ADD720-1C9B-46DE-AA31-D15AD37A45B0}",
      "county": "DENVER",
      "cause": "Outage",
      "city": "Denver",
      "xcelarea": "Denver"
    },
    "geometry": {
      "x": -11690273.817699999,
      "y": 4821866.0744000003
    }
  },
  {
    "attributes": {
      "objectid": 82882,
      "boundary": null,
      "comments": "Crews are working to restore power as quickly and safely as possible. Please continue to check back for estimated restoration time updates. Thank you for your patience.",
      "customers": 3,
      "off_": 1770972960000,
      "etr": 1770987600000,
      "ticket": "13095516",
      "outageimpact": "Small",
      "outagetype": "Unplanned Outage",
      "medialink": null,
      "outagestatus": 0,
      "datastatus": null,
      "latlong": "4953584.704000004,-11708190.6152",
      "states": "CO",
      "crewstatus": null,
      "globalid": "{0448E14F-D9AC-4CF6-9900-7697B4B592A9}",
      "county": "LARIMER",
      "cause": "Outage",
      "city": "Bellvue",
      "xcelarea": "Bellvue"
    },
    "geometry": {
      "x": -11708190.6152,
      "y": 4953584.7040000036
    }
  },
  {
    "attributes": {
      "objectid": 82780,
      "boundary": null,
      "comments": "Crews are working to restore power as quickly and safely as possible. Please continue to check back for estimated restoration time updates. Thank you for your patience.",
      "customers": 13,
      "off_": 1770964920000,
      "etr": 1770974100000,
      "ticket": "13095516",
      "outageimpact": "Small",
      "outagetype": "Unplanned Outage",
      "medialink": null,
      "outagestatus": 0,
      "datastatus": null,
      "latlong": "4655587.701700002,-11799319.615699999",
      "states": "CO",
      "crewstatus": null,
      "globalid": "{6D70E001-D1D4-4F47-804A-7793DC7E9B9B}",
      "county": "CHAFFEE",
      "cause": "Outage",
      "city": "Salida",
      "xcelarea": "Salida"
    },
    "geometry": {
      "x": -11799319.615699999,
      "y": 4655587.701700002
    }
  },
  {
    "attributes": {
      "objectid": 82845,
      "boundary": null,
      "comments": "Crews are working to restore power as quickly and safely as possible. Please continue to check back for estimated restoration time updates. Thank you for your patience.",
      "customers": 233,
      "off_": 1770974940000,
      "etr": 1770980400000,
      "ticket": "13095516",
      "outageimpact": "Medium",
      "outagetype": "Unplanned Outage",
      "medialink": null,
      "outagestatus": 0,
      "datastatus": null,
      "latlong": "4825638.775899999,-11711584.8099",
      "states": "CO",
      "crewstatus": null,
      "globalid": "{4C4AAD3C-B1E9-406E-8EA7-F369AA2E4A45}",
      "county": "JEFFERSON",
      "cause": "Outage",
      "city": "Golden",
      "xcelarea": "Golden"
    },
    "geometry": {
      "x": -11711584.809900001,
      "y": 4825638.7758999988
    }
  },
  {
    "attributes": {
      "objectid": 82922,
      "boundary": null,
      "comments": "Crews are working to restore power as quickly and safely as possible. Please continue to check back for estimated restoration time updates. Thank you for your patience.",
      "customers": 1,
      "off_": 1770975180000,
      "etr": 1770981300000,
      "ticket": "13095516",
      "outageimpact": "Small",
      "outagetype": "Unplanned Outage",
      "medialink": null,
      "outagestatus": 0,
      "datastatus": null,
      "latlong": "4824277.565099999,-11765602.4915",
      "states": "CO",
      "crewstatus": null,
      "globalid": "{6E3F4E96-A14D-48BA-BD1E-495C3F06B2F8}",
      "county": "CLEAR CREEK",
      "cause": "Outage",
      "city": "Georgetown",
      "xcelarea": "Georgetown"
    },
    "geometry": {
      "x": -11765602.4915,
      "y": 4824277.5650999993
    }
  },
  {
    "attributes": {
      "objectid": 82884,
      "boundary": null,
      "comments": "Crews are working to restore power as quickly and safely as possible. Please continue to check back for estimated restoration time updates. Thank you for your patience.",
      "customers": 33,
      "off_": 1770973200000,
      "etr": 1770982200000,
      "ticket": "13095516",
      "outageimpact": "Small",
      "outagetype": "Unplanned Outage",
      "medialink": null,
      "outagestatus": 0,
      "datastatus": null,
      "latlong": "4826458.8347999975,-11692013.1725",
      "states": "CO",
      "crewstatus": null,
      "globalid": "{206E65F2-05FA-49D4-AE3A-4F477C3A4B93}",
      "county": "DENVER",
      "cause": "Outage",
      "city": "Denver",
      "xcelarea": "Denver"
    },
    "geometry": {
      "x": -11692013.172499999,
      "y": 4826458.8347999975
    }
  },
  {
    "attributes": {
      "objectid": 82885,
      "boundary": null,
      "comments": "Crews are working to restore power as quickly and safely as possible. Please continue to check back for estimated restoration time updates. Thank you for your patience.",
      "customers": 1,
      "off_": 1770974160000,
      "etr": 1770984900000,
      "ticket": "13095516",
      "outageimpact": "Small",
      "outagetype": "Unplanned Outage",
      "medialink": null,
      "outagestatus": 0,
      "datastatus": null,
      "latlong": "4848489.485399999,-11690864.2774",
      "states": "CO",
      "crewstatus": null,
      "globalid": "{D5567ED8-4F08-43F3-8148-F6346E5FC239}",
      "county": "ADAMS",
      "cause": "Outage",
      "city": "Federal Heights",
      "xcelarea": "Federal Heights"
    },
    "geometry": {
      "x": -11690864.2774,
      "y": 4848489.4853999987
    }
  },
  {
    "attributes": {
      "objectid": 82878,
      "boundary": null,
      "comments": "Crews are working to restore power as quickly and safely as possible. Please continue to check back for estimated restoration time updates. Thank you for your patience.",
      "customers": 1,
      "off_": 1770972060000,
      "etr": 1770990300000,
      "ticket": "13095516",
      "outageimpact": "Small",
      "outagetype": "Unplanned Outage",
      "medialink": null,
      "outagestatus": 0,
      "datastatus": null,
      "latlong": "4931439.644000001,-11656889.3551",
      "states": "CO",
      "crewstatus": null,
      "globalid": "{F3B1B764-8EB9-4035-ADCC-44B1F584FBF6}",
      "county": "WELD",
      "cause": "Outage",
      "city": "Greeley",
      "xcelarea": "Greeley"
    },
    "geometry": {
      "x": -11656889.3551,
      "y": 4931439.6440000013
    }
  },
  {
    "attributes": {
      "objectid": 82854,
      "boundary": null,
      "comments": "Crews are in the area working to restore power as quickly and safely as possible. Please continue to check back for estimated restoration time updates. Thank you for your patience.",
      "customers": 1,
      "off_": 1770971820000,
      "etr": 1770979500000,
      "ticket": "13095516",
      "outageimpact": "Small",
      "outagetype": "Unplanned Outage",
      "medialink": null,
      "outagestatus": 0,
      "datastatus": null,
      "latlong": "4818681.986199997,-11672471.0426",
      "states": "CO",
      "crewstatus": "Crew Onsite",
      "globalid": "{C8ADC159-01DA-40F1-9CDA-443BFFC40FE3}",
      "county": "ARAPAHOE",
      "cause": "Outage",
      "city": "Aurora",
      "xcelarea": "Aurora"
    },
    "geometry": {
      "x": -11672471.0426,
      "y": 4818681.9861999974
    }
  },
  {
    "attributes": {
      "objectid": 82835,
      "boundary": null,
      "comments": "Crews are working to restore power as quickly and safely as possible. Please continue to check back for estimated restoration time updates. Thank you for your patience.",
      "customers": 3,
      "off_": 1770971100000,
      "etr": 1771000200000,
      "ticket": "13095516",
      "outageimpact": "Small",
      "outagetype": "Unplanned Outage",
      "medialink": null,
      "outagestatus": 0,
      "datastatus": null,
      "latlong": "4808355.370399997,-11696982.243",
      "states": "CO",
      "crewstatus": null,
      "globalid": "{CEEF48D0-D672-4E87-92DF-9F3EC496A9E0}",
      "county": "JEFFERSON",
      "cause": "Outage",
      "city": "Littleton",
      "xcelarea": "Littleton"
    },
    "geometry": {
      "x": -11696982.243000001,
      "y": 4808355.3703999966
    }
  },
  {
    "attributes": {
      "objectid": 82941,
      "boundary": null,
      "comments": "The outage has been reported. Please continue to check back for additional updates regarding the restoration progress.",
      "customers": 1,
      "off_": 1770976020000,
      "etr": 1770987600000,
      "ticket": "13095516",
      "outageimpact": "Small",
      "outagetype": "Unplanned Outage",
      "medialink": null,
      "outagestatus": 0,
      "datastatus": null,
      "latlong": "4855467.117700003,-11695079.9288",
      "states": "CO",
      "crewstatus": null,
      "globalid": "{76AC55E5-EA0C-4618-AB45-662AEEB4FB48}",
      "county": "BROOMFIELD",
      "cause": "Outage",
      "city": "Broomfield",
      "xcelarea": "Broomfield"
    },
    "geometry": {
      "x": -11695079.9288,
      "y": 4855467.1177000031
    }
  },
  {
    "attributes": {
      "objectid": 82942,
      "boundary": null,
      "comments": "The outage has been reported. Please continue to check back for additional updates regarding the restoration progress.",
      "customers": 1,
      "off_": 1770976200000,
      "etr": 1770987600000,
      "ticket": "13095516",
      "outageimpact": "Small",
      "outagetype": "Unplanned Outage",
      "medialink": null,
      "outagestatus": 0,
      "datastatus": null,
      "latlong": "4804248.888599999,-11681021.9201",
      "states": "CO",
      "crewstatus": null,
      "globalid": "{A7F97B47-030D-47A0-A4FA-A9F4AC5342D4}",
      "county": "ARAPAHOE",
      "cause": "Outage",
      "city": "Centennial",
      "xcelarea": "Centennial"
    },
    "geometry": {
      "x": -11681021.9201,
      "y": 4804248.8885999992
    }
  },
  {
    "attributes": {
      "objectid": 82943,
      "boundary": null,
      "comments": "The outage has been reported. Please continue to check back for additional updates regarding the restoration progress.",
      "customers": 10,
      "off_": 1770976260000,
      "etr": 1770987600000,
      "ticket": "13095516",
      "outageimpact": "Small",
      "outagetype": "Unplanned Outage",
      "medialink": null,
      "outagestatus": 0,
      "datastatus": null,
      "latlong": "4865050.171800002,-11698768.7773",
      "states": "CO",
      "crewstatus": null,
      "globalid": "{FC7D7685-2A3D-4C47-A83B-CE9D7BD539EF}",
      "county": "BOULDER",
      "cause": "Outage",
      "city": "Lafayette",
      "xcelarea": "Lafayette"
    },
    "geometry": {
      "x": -11698768.7773,
      "y": 4865050.1718000025
    }
  },
  {
    "attributes": {
      "objectid": 82944,
      "boundary": null,
      "comments": "The outage has been reported. Please continue to check back for additional updates regarding the restoration progress.",
      "customers": 1,
      "off_": 1770976260000,
      "etr": 1770987600000,
      "ticket": "13095516",
      "outageimpact": "Small",
      "outagetype": "Unplanned Outage",
      "medialink": null,
      "outagestatus": 0,
      "datastatus": null,
      "latlong": "4864899.573899999,-11698764.1887",
      "states": "CO",
      "crewstatus": null,
      "globalid": "{A2D8B0A6-1AB2-4A85-A5A8-E7837CED5D6D}",
      "county": "BOULDER",
      "cause": "Outage",
      "city": "Lafayette",
      "xcelarea": "Lafayette"
    },
    "geometry": {
      "x": -11698764.1887,
      "y": 4864899.5738999993
    }
  },
  {
    "attributes": {
      "objectid": 82853,
      "boundary": null,
      "comments": "Crews are working to restore power as quickly and safely as possible. Please continue to check back for estimated restoration time updates. Thank you for your patience.",
      "customers": 1,
      "off_": 1770971700000,
      "etr": 1770987600000,
      "ticket": "13095516",
      "outageimpact": "Small",
      "outagetype": "Unplanned Outage",
      "medialink": null,
      "outagestatus": 0,
      "datastatus": null,
      "latlong": "4907407.069200002,-11682012.243900001",
      "states": "CO",
      "crewstatus": null,
      "globalid": "{F7143FF0-476F-4F26-9A19-E87ABAE3CE25}",
      "county": "WELD",
      "cause": "Outage",
      "city": "Johnstown",
      "xcelarea": "Johnstown"
    },
    "geometry": {
      "x": -11682012.243900001,
      "y": 4907407.0692000017
    }
  },
  {
    "attributes": {
      "objectid": 82838,
      "boundary": null,
      "comments": "Crews are working to restore power as quickly and safely as possible. Please continue to check back for estimated restoration time updates. Thank you for your patience.",
      "customers": 1,
      "off_": 1770971100000,
      "etr": 1770981300000,
      "ticket": "13095516",
      "outageimpact": "Small",
      "outagetype": "Unplanned Outage",
      "medialink": null,
      "outagestatus": 0,
      "datastatus": null,
      "latlong": "4840238.780599996,-11706809.4965",
      "states": "CO",
      "crewstatus": null,
      "globalid": "{5A55BB6A-19D6-4B05-89A3-D5B1E2797996}",
      "county": "JEFFERSON",
      "cause": "Outage",
      "city": "Arvada",
      "xcelarea": "Arvada"
    },
    "geometry": {
      "x": -11706809.4965,
      "y": 4840238.7805999964
    }
  },
  {
    "attributes": {
      "objectid": 82807,
      "boundary": null,
      "comments": "Crews are working to restore power as quickly and safely as possible. Please continue to check back for estimated restoration time updates. Thank you for your patience.",
      "customers": 1,
      "off_": 1770969060000,
      "etr": 1770974100000,
      "ticket": "13095516",
      "outageimpact": "Small",
      "outagetype": "Unplanned Outage",
      "medialink": null,
      "outagestatus": 0,
      "datastatus": null,
      "latlong": "4494636.931900002,-11733917.3287",
      "states": "CO",
      "crewstatus": null,
      "globalid": "{73BC9CBA-1637-4700-9D1A-9497B76E2CDE}",
      "county": "COSTILLA",
      "cause": "Outage",
      "city": "Fort Garland",
      "xcelarea": "Fort Garland"
    },
    "geometry": {
      "x": -11733917.3287,
      "y": 4494636.9319000021
    }
  }
]
