[
  {
    "attributes": {
      "objectid": 67933,
      "boundary": null,
      "comments": "Crews are in the area working to restore power as quickly and safely as possible. Please continue to check back for estimated restoration time updates. Thank you for your patience.",
      "customers": 1,
      "off_": 1769401680000,
      "etr": 1769408100000,
      "ticket": "26044533",
      "outageimpact": "Small",
      "outagetype": "Unplanned Outage",
      "medialink": null,
      "outagestatus": 0,
      "datastatus": null,
      "latlong": "4823652.675399996,-11684420.8716",
      "states": "CO",
      "crewstatus": "Crew Onsite",
      "globalid": "{C1BE943E-BC32-4107-B00F-838F55FB171C}",
      "county": "DENVER",
      "cause": "Outage",
      "city": "Denver",
      "xcelarea": "Denver"
    },
    "geometry": {
      "x": -11684420.8716,
      "y": 4823652.6753999963
    }
  },
  {
    "attributes": {
      "objectid": 67884,
      "boundary": null,
      "comments": "Crews are working to restore power as quickly and safely as possible. Please continue to check back for estimated restoration time updates. Thank you for your patience.",
      "customers": 1656,
      "off_": 1769392440000,
      "etr": 1769417100000,
      "ticket": "26044533",
      "outageimpact": "Large",
      "outagetype": "Unplanned Outage",
      "medialink": null,
      "outagestatus": 0,
      "datastatus": null,
      "latlong": "4942306.2842999995,-11657957.148400001",
      "states": "CO",
      "crewstatus": null,
      "globalid": "{538E495A-ECFA-4ABC-BD4F-A2B69FE2F646}",
      "county": "WELD",
      "cause": "Outage",
      "city": "Greeley,  Ault,  Severance,  Eaton",
      "xcelarea": "Greeley,  Ault,  Severance,  Eaton"
    },
    "geometry": {
      "x": -11657957.148400001,
      "y": 4942306.2842999995
    }
  },
  {
    "attributes": {
      "objectid": 67766,
      "boundary": null,
      "comments": "Crews are working to restore power as quickly and safely as possible. Please continue to check back for estimated restoration time updates. Thank you for your patience.",
      "customers": 1,
      "off_": 1769367780000,
      "etr": 1769445900000,
      "ticket": "26044533",
      "outageimpact": "Small",
      "outagetype": "Unplanned Outage",
      "medialink": null,
      "outagestatus": 0,
      "datastatus": null,
      "latlong": "4899699.009000003,-11666028.9224",
      "states": "CO",
      "crewstatus": null,
      "globalid": "{8E263E6B-3185-4111-A060-77B0D15CFF7A}",
      "county": "WELD",
      "cause": "Outage",
      "city": "Platteville",
      "xcelarea": "Platteville"
    },
    "geometry": {
      "x": -11666028.9224,
      "y": 4899699.0090000033
    }
  },
  {
    "attributes": {
      "objectid": 67922,
      "boundary": null,
      "comments": "Crews are working to restore power as quickly and safely as possible. Please continue to check back for estimated restoration time updates. Thank you for your patience.",
      "customers": 150,
      "off_": 1769394720000,
      "etr": 1769417100000,
      "ticket": "26044533",
      "outageimpact": "Medium",
      "outagetype": "Unplanned Outage",
      "medialink": null,
      "outagestatus": 0,
      "datastatus": null,
      "latlong": "4903263.392700002,-11537671.1275",
      "states": "CO",
      "crewstatus": null,
      "globalid": "{ED2BB05B-89DA-4C2A-8BCF-E921C9730270}",
      "county": "MORGAN",
      "cause": "Outage",
      "city": "Brush",
      "xcelarea": "Brush"
    },
    "geometry": {
      "x": -11537671.127499999,
      "y": 4903263.3927000016
    }
  },
  {
    "attributes": {
      "objectid": 67917,
      "boundary": null,
      "comments": "Crews are in the area working to restore power as quickly and safely as possible. Please continue to check back for estimated restoration time updates. Thank you for your patience.",
      "customers": 123,
      "off_": 1769394540000,
      "etr": 1769417100000,
      "ticket": "26044533",
      "outageimpact": "Medium",
      "outagetype": "Unplanned Outage",
      "medialink": null,
      "outagestatus": 0,
      "datastatus": null,
      "latlong": "4903310.081699997,-11537688.824",
      "states": "CO",
      "crewstatus": "Crew Onsite",
      "globalid": "{DC18D056-8A4B-4C02-943C-7D4939308BBA}",
      "county": "MORGAN",
      "cause": "Outage",
      "city": "Brush",
      "xcelarea": "Brush"
    },
    "geometry": {
      "x": -11537688.823999999,
      "y": 4903310.0816999972
    }
  },
  {
    "attributes": {
      "objectid": 67903,
      "boundary": null,
      "comments": "Crews are working to restore power as quickly and safely as possible. Please continue to check back for estimated restoration time updates. Thank you for your patience.",
      "customers": 24,
      "off_": 1769394840000,
      "etr": 1769417100000,
      "ticket": "26044533",
      "outageimpact": "Small",
      "outagetype": "Unplanned Outage",
      "medialink": null,
      "outagestatus": 0,
      "datastatus": null,
      "latlong": "4824561.536799997,-11680937.8283",
      "states": "CO",
      "crewstatus": null,
      "globalid": "{37E12C1B-45F8-45D8-B0B5-B0D832789C91}",
      "county": "DENVER",
      "cause": "Outage",
      "city": "Denver",
      "xcelarea": "Denver"
    },
    "geometry": {
      "x": -11680937.828299999,
      "y": 4824561.5367999971
    }
  }
]
