[
  {
    "attributes": {
      "objectid": 89248,
      "boundary": null,
      "comments": "The outage has been reported. Please continue to check back for additional updates regarding the restoration progress.",
      "customers": 2,
      "off_": 1771934820000,
      "etr": 1771941600000,
      "ticket": "24123628",
      "outageimpact": "Small",
      "outagetype": "Unplanned Outage",
      "medialink": null,
      "outagestatus": 0,
      "datastatus": null,
      "latlong": "4838263.389200002,-11703203.2359",
      "states": "CO",
      "crewstatus": null,
      "globalid": "{427D6615-04F8-4E1A-AC15-B6A8ACD3201B}",
      "county": "JEFFERSON",
      "cause": "Outage",
      "city": "Arvada",
      "xcelarea": "Arvada"
    },
    "geometry": {
      "x": -11703203.2359,
      "y": 4838263.389200002
    }
  },
  {
    "attributes": {
      "objectid": 88971,
      "boundary": null,
      "comments": "Crews are working to restore power as quickly and safely as possible. Please continue to check back for estimated restoration time updates. Thank you for your patience.",
      "customers": 3,
      "off_": 1771921620000,
      "etr": 1771939800000,
      "ticket": "24123628",
      "outageimpact": "Small",
      "outagetype": "Unplanned Outage",
      "medialink": null,
      "outagestatus": 0,
      "datastatus": null,
      "latlong": "4968567.992600001,-11664732.1339",
      "states": "CO",
      "crewstatus": null,
      "globalid": "{B350C67C-37E2-4818-807B-DDD2E5666D69}",
      "county": "WELD",
      "cause": "Outage",
      "city": "Nunn",
      "xcelarea": "Nunn"
    },
    "geometry": {
      "x": -11664732.1339,
      "y": 4968567.9926000014
    }
  },
  {
    "attributes": {
      "objectid": 89264,
      "boundary": null,
      "comments": "The outage has been reported. Please continue to check back for additional updates regarding the restoration progress.",
      "customers": 2,
      "off_": 1771935960000,
      "etr": 1771945200000,
      "ticket": "24123628",
      "outageimpact": "Small",
      "outagetype": "Unplanned Outage",
      "medialink": null,
      "outagestatus": 0,
      "datastatus": null,
      "latlong": "4842099.772399999,-11686049.4434",
      "states": "CO",
      "crewstatus": null,
      "globalid": "{7B747072-E21F-4BB9-815D-10563DBFC70E}",
      "county": "ADAMS",
      "cause": "Outage",
      "city": "Denver",
      "xcelarea": "Denver"
    },
    "geometry": {
      "x": -11686049.443399999,
      "y": 4842099.7723999992
    }
  },
  {
    "attributes": {
      "objectid": 89266,
      "boundary": null,
      "comments": "The outage has been reported. Please continue to check back for additional updates regarding the restoration progress.",
      "customers": 1,
      "off_": 1771936080000,
      "etr": 1771947000000,
      "ticket": "24123628",
      "outageimpact": "Small",
      "outagetype": "Unplanned Outage",
      "medialink": null,
      "outagestatus": 0,
      "datastatus": null,
      "latlong": "4833939.409400001,-11702054.7427",
      "states": "CO",
      "crewstatus": null,
      "globalid": "{9C8ED927-9841-4E24-A97E-AF4B3C67E411}",
      "county": "JEFFERSON",
      "cause": "Outage",
      "city": "Wheat Ridge",
      "xcelarea": "Wheat Ridge"
    },
    "geometry": {
      "x": -11702054.742699999,
      "y": 4833939.4094000012
    }
  },
  {
    "attributes": {
      "objectid": 88949,
      "boundary": null,
      "comments": "Crews are working to restore power as quickly and safely as possible. Please continue to check back for estimated restoration time updates. Thank you for your patience.",
      "customers": 1,
      "off_": 1771920180000,
      "etr": 1771941600000,
      "ticket": "24123628",
      "outageimpact": "Small",
      "outagetype": "Unplanned Outage",
      "medialink": null,
      "outagestatus": 0,
      "datastatus": null,
      "latlong": "4804962.706799999,-11721152.3806",
      "states": "CO",
      "crewstatus": null,
      "globalid": "{F31D57BD-A701-448F-8E3F-CF7067A0AFAE}",
      "county": "JEFFERSON",
      "cause": "Outage",
      "city": "Evergreen",
      "xcelarea": "Evergreen"
    },
    "geometry": {
      "x": -11721152.3806,
      "y": 4804962.7067999989
    }
  },
  {
    "attributes": {
      "objectid": 89007,
      "boundary": null,
      "comments": "Crews are working to restore power as quickly and safely as possible. Please continue to check back for estimated restoration time updates. Thank you for your patience.",
      "customers": 9,
      "off_": 1771922640000,
      "etr": 1771939800000,
      "ticket": "24123628",
      "outageimpact": "Small",
      "outagetype": "Unplanned Outage",
      "medialink": null,
      "outagestatus": 0,
      "datastatus": null,
      "latlong": "4862811.7368,-11716804.238",
      "states": "CO",
      "crewstatus": null,
      "globalid": "{9D69C2C2-F496-4E92-B617-4B64D17868EF}",
      "county": "BOULDER",
      "cause": "Outage",
      "city": "Boulder",
      "xcelarea": "Boulder"
    },
    "geometry": {
      "x": -11716804.238,
      "y": 4862811.7368000001
    }
  },
  {
    "attributes": {
      "objectid": 89010,
      "boundary": null,
      "comments": "Crews are working to restore power as quickly and safely as possible. Please continue to check back for estimated restoration time updates. Thank you for your patience.",
      "customers": 5,
      "off_": 1771922760000,
      "etr": 1771952400000,
      "ticket": "24123628",
      "outageimpact": "Small",
      "outagetype": "Unplanned Outage",
      "medialink": null,
      "outagestatus": 0,
      "datastatus": null,
      "latlong": "4946541.085600004,-11704693.7126",
      "states": "CO",
      "crewstatus": null,
      "globalid": "{339AC62A-C976-48E8-95C8-52B5ED87F12F}",
      "county": "LARIMER",
      "cause": "Outage",
      "city": "Fort Collins",
      "xcelarea": "Fort Collins"
    },
    "geometry": {
      "x": -11704693.7126,
      "y": 4946541.0856000036
    }
  },
  {
    "attributes": {
      "objectid": 89120,
      "boundary": null,
      "comments": "Crews are working to restore power as quickly and safely as possible. Please continue to check back for estimated restoration time updates. Thank you for your patience.",
      "customers": 3,
      "off_": 1771926180000,
      "etr": null,
      "ticket": "24123628",
      "outageimpact": "Small",
      "outagetype": "Unplanned Outage",
      "medialink": null,
      "outagestatus": 0,
      "datastatus": null,
      "latlong": "4831388.299999997,-11662416.5816",
      "states": "CO",
      "crewstatus": null,
      "globalid": "{F2F81184-983C-4E81-8C92-B53163D693BE}",
      "county": "ADAMS",
      "cause": "Outage",
      "city": "Aurora",
      "xcelarea": "Aurora"
    },
    "geometry": {
      "x": -11662416.581599999,
      "y": 4831388.299999997
    }
  },
  {
    "attributes": {
      "objectid": 89243,
      "boundary": null,
      "comments": "Crews are working to restore power as quickly and safely as possible. Please continue to check back for estimated restoration time updates. Thank you for your patience.",
      "customers": 3,
      "off_": 1771934280000,
      "etr": 1771941600000,
      "ticket": "24123628",
      "outageimpact": "Small",
      "outagetype": "Unplanned Outage",
      "medialink": null,
      "outagestatus": 0,
      "datastatus": null,
      "latlong": "4792868.257200003,-11674739.987599999",
      "states": "CO",
      "crewstatus": null,
      "globalid": "{B4E48677-C20C-4646-A5FF-30F79D5FCBE5}",
      "county": "DOUGLAS",
      "cause": "Outage",
      "city": "Castle Rock",
      "xcelarea": "Castle Rock"
    },
    "geometry": {
      "x": -11674739.987599999,
      "y": 4792868.2572000027
    }
  },
  {
    "attributes": {
      "objectid": 88979,
      "boundary": null,
      "comments": "Crews are working to restore power as quickly and safely as possible. Please continue to check back for estimated restoration time updates. Thank you for your patience.",
      "customers": 6,
      "off_": 1771921740000,
      "etr": 1771938900000,
      "ticket": "24123628",
      "outageimpact": "Small",
      "outagetype": "Unplanned Outage",
      "medialink": null,
      "outagestatus": 0,
      "datastatus": null,
      "latlong": "4968753.305299997,-11664731.0118",
      "states": "CO",
      "crewstatus": null,
      "globalid": "{7E2DD702-A427-430B-AB26-BB70B47BD728}",
      "county": "WELD",
      "cause": "Outage",
      "city": "Nunn",
      "xcelarea": "Nunn"
    },
    "geometry": {
      "x": -11664731.0118,
      "y": 4968753.3052999973
    }
  },
  {
    "attributes": {
      "objectid": 89253,
      "boundary": null,
      "comments": "Crews are working to restore power as quickly and safely as possible. Please continue to check back for estimated restoration time updates. Thank you for your patience.",
      "customers": 1,
      "off_": 1771934880000,
      "etr": 1771940700000,
      "ticket": "24123628",
      "outageimpact": "Small",
      "outagetype": "Unplanned Outage",
      "medialink": null,
      "outagestatus": 0,
      "datastatus": null,
      "latlong": "4814576.045299999,-11733868.2691",
      "states": "CO",
      "crewstatus": null,
      "globalid": "{C1637B4F-D82D-4AEC-8416-088B4E20B2F7}",
      "county": "CLEAR CREEK",
      "cause": "Outage",
      "city": "Evergreen",
      "xcelarea": "Evergreen"
    },
    "geometry": {
      "x": -11733868.269099999,
      "y": 4814576.0452999994
    }
  },
  {
    "attributes": {
      "objectid": 89090,
      "boundary": null,
      "comments": "Crews are working to restore power as quickly and safely as possible. Please continue to check back for estimated restoration time updates. Thank you for your patience.",
      "customers": 0,
      "off_": 1771925940000,
      "etr": null,
      "ticket": "24123628",
      "outageimpact": "Small",
      "outagetype": "Unplanned Outage",
      "medialink": null,
      "outagestatus": 0,
      "datastatus": null,
      "latlong": "4813198.932899997,-11678683.9893",
      "states": "CO",
      "crewstatus": null,
      "globalid": "{51068154-FABD-40F0-82B7-0E3D191D13AE}",
      "county": "DENVER",
      "cause": "Outage",
      "city": "Denver",
      "xcelarea": "Denver"
    },
    "geometry": {
      "x": -11678683.9893,
      "y": 4813198.9328999966
    }
  },
  {
    "attributes": {
      "objectid": 89057,
      "boundary": null,
      "comments": "Crews are working to restore power as quickly and safely as possible. Please continue to check back for estimated restoration time updates. Thank you for your patience.",
      "customers": 10,
      "off_": 1771924560000,
      "etr": null,
      "ticket": "24123628",
      "outageimpact": "Small",
      "outagetype": "Unplanned Outage",
      "medialink": null,
      "outagestatus": 0,
      "datastatus": null,
      "latlong": "4872961.865099996,-11720074.845800001",
      "states": "CO",
      "crewstatus": null,
      "globalid": "{C6BF0DB4-EBF3-4BAF-861F-146A047FE005}",
      "county": "BOULDER",
      "cause": "Outage",
      "city": "Boulder",
      "xcelarea": "Boulder"
    },
    "geometry": {
      "x": -11720074.845800001,
      "y": 4872961.8650999963
    }
  },
  {
    "attributes": {
      "objectid": 88922,
      "boundary": null,
      "comments": "Crews are working to restore power as quickly and safely as possible. Please continue to check back for estimated restoration time updates. Thank you for your patience.",
      "customers": 27,
      "off_": 1771916160000,
      "etr": 1771975800000,
      "ticket": "24123628",
      "outageimpact": "Small",
      "outagetype": "Unplanned Outage",
      "medialink": null,
      "outagestatus": 0,
      "datastatus": null,
      "latlong": "4655890.623899996,-11799586.502",
      "states": "CO",
      "crewstatus": null,
      "globalid": "{EC57BB11-B99C-486F-8C03-A8FCA71533A5}",
      "county": "CHAFFEE",
      "cause": "Outage",
      "city": "Salida",
      "xcelarea": "Salida"
    },
    "geometry": {
      "x": -11799586.502,
      "y": 4655890.6238999963
    }
  },
  {
    "attributes": {
      "objectid": 89039,
      "boundary": null,
      "comments": "Crews are working to restore power as quickly and safely as possible. Please continue to check back for estimated restoration time updates. Thank you for your patience.",
      "customers": 7,
      "off_": 1771924020000,
      "etr": 1771953300000,
      "ticket": "24123628",
      "outageimpact": "Small",
      "outagetype": "Unplanned Outage",
      "medialink": null,
      "outagestatus": 0,
      "datastatus": null,
      "latlong": "4828006.712399997,-11764601.3118",
      "states": "CO",
      "crewstatus": null,
      "globalid": "{5734BC45-40AF-41F3-9878-0752D7CD5CB7}",
      "county": "CLEAR CREEK",
      "cause": "Outage",
      "city": "Georgetown",
      "xcelarea": "Georgetown"
    },
    "geometry": {
      "x": -11764601.311799999,
      "y": 4828006.7123999968
    }
  },
  {
    "attributes": {
      "objectid": 88980,
      "boundary": null,
      "comments": "Crews are working to restore power as quickly and safely as possible. Please continue to check back for estimated restoration time updates. Thank you for your patience.",
      "customers": 8,
      "off_": 1771921740000,
      "etr": 1771954200000,
      "ticket": "24123628",
      "outageimpact": "Small",
      "outagetype": "Unplanned Outage",
      "medialink": null,
      "outagestatus": 0,
      "datastatus": null,
      "latlong": "4877885.2826000005,-11729778.9599",
      "states": "CO",
      "crewstatus": null,
      "globalid": "{E9F47EEF-DAB0-47FE-9097-ED98ED7E46C8}",
      "county": "BOULDER",
      "cause": "Outage",
      "city": "Jamestown",
      "xcelarea": "Jamestown"
    },
    "geometry": {
      "x": -11729778.959899999,
      "y": 4877885.2826000005
    }
  },
  {
    "attributes": {
      "objectid": 89164,
      "boundary": null,
      "comments": "Crews are working to restore power as quickly and safely as possible. Please continue to check back for estimated restoration time updates. Thank you for your patience.",
      "customers": 8,
      "off_": 1771929240000,
      "etr": 1771943400000,
      "ticket": "24123628",
      "outageimpact": "Small",
      "outagetype": "Unplanned Outage",
      "medialink": null,
      "outagestatus": 0,
      "datastatus": null,
      "latlong": "4812822.059600003,-11688504.4089",
      "states": "CO",
      "crewstatus": null,
      "globalid": "{1F5EAD41-C9F6-4CF4-8FD2-1063A66D8297}",
      "county": "ARAPAHOE",
      "cause": "Outage",
      "city": "Englewood",
      "xcelarea": "Englewood"
    },
    "geometry": {
      "x": -11688504.4089,
      "y": 4812822.0596000031
    }
  },
  {
    "attributes": {
      "objectid": 89259,
      "boundary": null,
      "comments": "Crews are working to restore power as quickly and safely as possible. Please continue to check back for estimated restoration time updates. Thank you for your patience.",
      "customers": 1,
      "off_": 1771935780000,
      "etr": 1771945200000,
      "ticket": "24123628",
      "outageimpact": "Small",
      "outagetype": "Unplanned Outage",
      "medialink": null,
      "outagestatus": 0,
      "datastatus": null,
      "latlong": "4818600.7368,-11681696.7812",
      "states": "CO",
      "crewstatus": null,
      "globalid": "{E7A4A681-F549-4944-87B9-C7377B9FC96A}",
      "county": "DENVER",
      "cause": "Outage",
      "city": "Denver",
      "xcelarea": "Denver"
    },
    "geometry": {
      "x": -11681696.781199999,
      "y": 4818600.7368000001
    }
  },
  {
    "attributes": {
      "objectid": 89263,
      "boundary": null,
      "comments": "The outage has been reported. Please continue to check back for additional updates regarding the restoration progress.",
      "customers": 1,
      "off_": 1771935960000,
      "etr": 1771947000000,
      "ticket": "24123628",
      "outageimpact": "Small",
      "outagetype": "Unplanned Outage",
      "medialink": null,
      "outagestatus": 0,
      "datastatus": null,
      "latlong": "4811714.708800003,-11677217.2381",
      "states": "CO",
      "crewstatus": null,
      "globalid": "{584A8B34-182B-43C8-83A0-32BD0FCA67CD}",
      "county": "DENVER",
      "cause": "Outage",
      "city": "Denver",
      "xcelarea": "Denver"
    },
    "geometry": {
      "x": -11677217.2381,
      "y": 4811714.7088000029
    }
  },
  {
    "attributes": {
      "objectid": 89050,
      "boundary": null,
      "comments": "Crews are working to restore power as quickly and safely as possible. Please continue to check back for estimated restoration time updates. Thank you for your patience.",
      "customers": 5,
      "off_": 1771923720000,
      "etr": null,
      "ticket": "24123628",
      "outageimpact": "Small",
      "outagetype": "Unplanned Outage",
      "medialink": null,
      "outagestatus": 0,
      "datastatus": null,
      "latlong": "4496150.195500001,-11727867.2124",
      "states": "CO",
      "crewstatus": null,
      "globalid": "{306B5B98-8643-4BDA-A681-9BC14BF399AA}",
      "county": "COSTILLA",
      "cause": "Outage",
      "city": "Fort Garland",
      "xcelarea": "Fort Garland"
    },
    "geometry": {
      "x": -11727867.212400001,
      "y": 4496150.1955000013
    }
  },
  {
    "attributes": {
      "objectid": 89260,
      "boundary": null,
      "comments": "Crews are working to restore power as quickly and safely as possible. Please continue to check back for estimated restoration time updates. Thank you for your patience.",
      "customers": 35,
      "off_": 1771935720000,
      "etr": 1771942500000,
      "ticket": "24123628",
      "outageimpact": "Small",
      "outagetype": "Unplanned Outage",
      "medialink": null,
      "outagestatus": 0,
      "datastatus": null,
      "latlong": "4822634.252700001,-11677842.3071",
      "states": "CO",
      "crewstatus": null,
      "globalid": "{2384BF9C-35D3-4CE9-92AC-FDD4A73690F1}",
      "county": "DENVER",
      "cause": "Outage",
      "city": "Denver",
      "xcelarea": "Denver"
    },
    "geometry": {
      "x": -11677842.3071,
      "y": 4822634.252700001
    }
  },
  {
    "attributes": {
      "objectid": 89146,
      "boundary": null,
      "comments": "Crews are working to restore power as quickly and safely as possible. Please continue to check back for estimated restoration time updates. Thank you for your patience.",
      "customers": 1,
      "off_": 1771927860000,
      "etr": null,
      "ticket": "24123628",
      "outageimpact": "Small",
      "outagetype": "Unplanned Outage",
      "medialink": null,
      "outagestatus": 0,
      "datastatus": null,
      "latlong": "4860245.645000003,-11706577.6058",
      "states": "CO",
      "crewstatus": null,
      "globalid": "{43138EE9-1F62-4938-8A1B-8C2D4E1C477D}",
      "county": "BOULDER",
      "cause": "Outage",
      "city": "Louisville",
      "xcelarea": "Louisville"
    },
    "geometry": {
      "x": -11706577.605799999,
      "y": 4860245.6450000033
    }
  },
  {
    "attributes": {
      "objectid": 89015,
      "boundary": null,
      "comments": "Crews are working to restore power as quickly and safely as possible. Please continue to check back for estimated restoration time updates. Thank you for your patience.",
      "customers": 10,
      "off_": 1771923300000,
      "etr": 1771952400000,
      "ticket": "24123628",
      "outageimpact": "Small",
      "outagetype": "Unplanned Outage",
      "medialink": null,
      "outagestatus": 0,
      "datastatus": null,
      "latlong": "4831554.622500002,-11670678.3134",
      "states": "CO",
      "crewstatus": null,
      "globalid": "{1604A917-3324-4982-A25A-785EAF060766}",
      "county": "ADAMS",
      "cause": "Outage",
      "city": "Aurora",
      "xcelarea": "Aurora"
    },
    "geometry": {
      "x": -11670678.3134,
      "y": 4831554.6225000024
    }
  },
  {
    "attributes": {
      "objectid": 89201,
      "boundary": null,
      "comments": "Crews are working to restore power as quickly and safely as possible. Please continue to check back for estimated restoration time updates. Thank you for your patience.",
      "customers": 10,
      "off_": 1771931460000,
      "etr": 1771938900000,
      "ticket": "24123628",
      "outageimpact": "Small",
      "outagetype": "Unplanned Outage",
      "medialink": null,
      "outagestatus": 0,
      "datastatus": null,
      "latlong": "4821830.772200003,-11689182.7297",
      "states": "CO",
      "crewstatus": null,
      "globalid": "{B3453159-A204-4C2E-975B-97B5B7BDA82E}",
      "county": "DENVER",
      "cause": "Outage",
      "city": "Denver",
      "xcelarea": "Denver"
    },
    "geometry": {
      "x": -11689182.729699999,
      "y": 4821830.7722000033
    }
  },
  {
    "attributes": {
      "objectid": 89072,
      "boundary": null,
      "comments": "Crews are working to restore power as quickly and safely as possible. Please continue to check back for estimated restoration time updates. Thank you for your patience.",
      "customers": 2,
      "off_": 1771924920000,
      "etr": 1771957800000,
      "ticket": "24123628",
      "outageimpact": "Small",
      "outagetype": "Unplanned Outage",
      "medialink": null,
      "outagestatus": 0,
      "datastatus": null,
      "latlong": "4824698.230499998,-11716917.2339",
      "states": "CO",
      "crewstatus": null,
      "globalid": "{16B0982E-74EE-4838-A7D2-3E7BBABF4634}",
      "county": "JEFFERSON",
      "cause": "Outage",
      "city": "Golden",
      "xcelarea": "Golden"
    },
    "geometry": {
      "x": -11716917.233899999,
      "y": 4824698.2304999977
    }
  },
  {
    "attributes": {
      "objectid": 89187,
      "boundary": null,
      "comments": "Crews are working to restore power as quickly and safely as possible. Please continue to check back for estimated restoration time updates. Thank you for your patience.",
      "customers": 2,
      "off_": 1771930260000,
      "etr": 1771934400000,
      "ticket": "24123628",
      "outageimpact": "Small",
      "outagetype": "Unplanned Outage",
      "medialink": null,
      "outagestatus": 0,
      "datastatus": null,
      "latlong": "4812933.694700003,-11807336.0128",
      "states": "CO",
      "crewstatus": null,
      "globalid": "{90938717-7186-458A-B944-A2BE334E769E}",
      "county": "SUMMIT",
      "cause": "Outage",
      "city": "Silverthorne",
      "xcelarea": "Silverthorne"
    },
    "geometry": {
      "x": -11807336.012800001,
      "y": 4812933.6947000027
    }
  },
  {
    "attributes": {
      "objectid": 88974,
      "boundary": null,
      "comments": "Crews are working to restore power as quickly and safely as possible. Please continue to check back for estimated restoration time updates. Thank you for your patience.",
      "customers": 4,
      "off_": 1771921620000,
      "etr": 1771950600000,
      "ticket": "24123628",
      "outageimpact": "Small",
      "outagetype": "Unplanned Outage",
      "medialink": null,
      "outagestatus": 0,
      "datastatus": null,
      "latlong": "4877852.123499997,-11730033.6644",
      "states": "CO",
      "crewstatus": null,
      "globalid": "{B51A588A-C1B9-4D5F-A316-ACEB9641126B}",
      "county": "BOULDER",
      "cause": "Outage",
      "city": "Jamestown",
      "xcelarea": "Jamestown"
    },
    "geometry": {
      "x": -11730033.6644,
      "y": 4877852.123499997
    }
  },
  {
    "attributes": {
      "objectid": 89163,
      "boundary": null,
      "comments": "Crews are working to restore power as quickly and safely as possible. Please continue to check back for estimated restoration time updates. Thank you for your patience.",
      "customers": 7,
      "off_": 1771928940000,
      "etr": null,
      "ticket": "24123628",
      "outageimpact": "Small",
      "outagetype": "Unplanned Outage",
      "medialink": null,
      "outagestatus": 0,
      "datastatus": null,
      "latlong": "4845053.428499997,-11678234.387699999",
      "states": "CO",
      "crewstatus": null,
      "globalid": "{70D27AFE-4CCC-4503-8DAF-16BC6E5EFBC7}",
      "county": "ADAMS",
      "cause": "Outage",
      "city": "Henderson",
      "xcelarea": "Henderson"
    },
    "geometry": {
      "x": -11678234.387699999,
      "y": 4845053.4284999967
    }
  },
  {
    "attributes": {
      "objectid": 89105,
      "boundary": null,
      "comments": "Crews are working to restore power as quickly and safely as possible. Please continue to check back for estimated restoration time updates. Thank you for your patience.",
      "customers": 5,
      "off_": 1771926420000,
      "etr": 1771943400000,
      "ticket": "24123628",
      "outageimpact": "Small",
      "outagetype": "Unplanned Outage",
      "medialink": null,
      "outagestatus": 0,
      "datastatus": null,
      "latlong": "4821595.3675,-11697382.5023",
      "states": "CO",
      "crewstatus": null,
      "globalid": "{D67E97EA-9CE1-4BC9-8B3E-99EF7CF40664}",
      "county": "JEFFERSON",
      "cause": "Outage",
      "city": "Lakewood",
      "xcelarea": "Lakewood"
    },
    "geometry": {
      "x": -11697382.5023,
      "y": 4821595.3674999997
    }
  },
  {
    "attributes": {
      "objectid": 89035,
      "boundary": null,
      "comments": "Crews are working to restore power as quickly and safely as possible. Please continue to check back for estimated restoration time updates. Thank you for your patience.",
      "customers": 0,
      "off_": 1771923480000,
      "etr": null,
      "ticket": "24123628",
      "outageimpact": "Small",
      "outagetype": "Unplanned Outage",
      "medialink": null,
      "outagestatus": 0,
      "datastatus": null,
      "latlong": "4867362.779100001,-11714588.7753",
      "states": "CO",
      "crewstatus": null,
      "globalid": "{7458633C-ED2E-4CB3-9989-273A36B338DC}",
      "county": "BOULDER",
      "cause": "Outage",
      "city": "Boulder",
      "xcelarea": "Boulder"
    },
    "geometry": {
      "x": -11714588.7753,
      "y": 4867362.7791000009
    }
  },
  {
    "attributes": {
      "objectid": 88703,
      "boundary": null,
      "comments": "Crews are working to restore power as quickly and safely as possible. Please continue to check back for estimated restoration time updates. Thank you for your patience.",
      "customers": 9,
      "off_": 1771857120000,
      "etr": 1772217900000,
      "ticket": "24123628",
      "outageimpact": "Small",
      "outagetype": "Unplanned Outage",
      "medialink": null,
      "outagestatus": 0,
      "datastatus": null,
      "latlong": "4798146.012199998,-11687505.2641",
      "states": "CO",
      "crewstatus": null,
      "globalid": "{18F1D3DF-FF45-4B5A-AEF9-85244D60642A}",
      "county": "DOUGLAS",
      "cause": "Outage",
      "city": "Highlands Ranch",
      "xcelarea": "Highlands Ranch"
    },
    "geometry": {
      "x": -11687505.2641,
      "y": 4798146.0121999979
    }
  },
  {
    "attributes": {
      "objectid": 89005,
      "boundary": null,
      "comments": "Crews are working to restore power as quickly and safely as possible. Please continue to check back for estimated restoration time updates. Thank you for your patience.",
      "customers": 3,
      "off_": 1771922520000,
      "etr": 1771938900000,
      "ticket": "24123628",
      "outageimpact": "Small",
      "outagetype": "Unplanned Outage",
      "medialink": null,
      "outagestatus": 0,
      "datastatus": null,
      "latlong": "4832014.941600002,-11757805.8625",
      "states": "CO",
      "crewstatus": null,
      "globalid": "{264C9873-A6E2-4474-A75C-D3B7D57001C2}",
      "county": "CLEAR CREEK",
      "cause": "Outage",
      "city": "Idaho Springs,  Dumont",
      "xcelarea": "Idaho Springs,  Dumont"
    },
    "geometry": {
      "x": -11757805.862500001,
      "y": 4832014.9416000023
    }
  },
  {
    "attributes": {
      "objectid": 89154,
      "boundary": null,
      "comments": "Crews are working to restore power as quickly and safely as possible. Please continue to check back for estimated restoration time updates. Thank you for your patience.",
      "customers": 16,
      "off_": 1771928340000,
      "etr": 1771944300000,
      "ticket": "24123628",
      "outageimpact": "Small",
      "outagetype": "Unplanned Outage",
      "medialink": null,
      "outagestatus": 0,
      "datastatus": null,
      "latlong": "4823208.2168999985,-11684808.296799999",
      "states": "CO",
      "crewstatus": null,
      "globalid": "{A4144A5E-DA3D-4983-B6A1-7C0F6A4C61A5}",
      "county": "DENVER",
      "cause": "Outage",
      "city": "Denver",
      "xcelarea": "Denver"
    },
    "geometry": {
      "x": -11684808.296799999,
      "y": 4823208.2168999985
    }
  },
  {
    "attributes": {
      "objectid": 89234,
      "boundary": null,
      "comments": "Crews are working to restore power as quickly and safely as possible. Please continue to check back for estimated restoration time updates. Thank you for your patience.",
      "customers": 3,
      "off_": 1771933560000,
      "etr": 1771939800000,
      "ticket": "24123628",
      "outageimpact": "Small",
      "outagetype": "Unplanned Outage",
      "medialink": null,
      "outagestatus": 0,
      "datastatus": null,
      "latlong": "4805285.028300002,-11720935.8664",
      "states": "CO",
      "crewstatus": null,
      "globalid": "{5F0E9AA0-4A60-4F08-9F7B-B3ECA80617B2}",
      "county": "JEFFERSON",
      "cause": "Outage",
      "city": "Evergreen",
      "xcelarea": "Evergreen"
    },
    "geometry": {
      "x": -11720935.8664,
      "y": 4805285.0283000022
    }
  },
  {
    "attributes": {
      "objectid": 89142,
      "boundary": null,
      "comments": "Crews are working to restore power as quickly and safely as possible. Please continue to check back for estimated restoration time updates. Thank you for your patience.",
      "customers": 6,
      "off_": 1771927680000,
      "etr": null,
      "ticket": "24123628",
      "outageimpact": "Small",
      "outagetype": "Unplanned Outage",
      "medialink": null,
      "outagestatus": 0,
      "datastatus": null,
      "latlong": "4802765.137999997,-11701238.6974",
      "states": "CO",
      "crewstatus": null,
      "globalid": "{38509BE7-F179-487E-806A-F0F0F89973B8}",
      "county": "JEFFERSON",
      "cause": "Outage",
      "city": "Littleton",
      "xcelarea": "Littleton"
    },
    "geometry": {
      "x": -11701238.6974,
      "y": 4802765.1379999965
    }
  },
  {
    "attributes": {
      "objectid": 89049,
      "boundary": null,
      "comments": "Crews are working to restore power as quickly and safely as possible. Please continue to check back for estimated restoration time updates. Thank you for your patience.",
      "customers": 4,
      "off_": 1771924500000,
      "etr": 1771940700000,
      "ticket": "24123628",
      "outageimpact": "Small",
      "outagetype": "Unplanned Outage",
      "medialink": null,
      "outagestatus": 0,
      "datastatus": null,
      "latlong": "4823523.0616,-11682838.0141",
      "states": "CO",
      "crewstatus": null,
      "globalid": "{2B7652BA-123B-4308-ABB1-A39F34A698EA}",
      "county": "DENVER",
      "cause": "Outage",
      "city": "Denver",
      "xcelarea": "Denver"
    },
    "geometry": {
      "x": -11682838.0141,
      "y": 4823523.0615999997
    }
  },
  {
    "attributes": {
      "objectid": 89053,
      "boundary": null,
      "comments": "Crews are working to restore power as quickly and safely as possible. Please continue to check back for estimated restoration time updates. Thank you for your patience.",
      "customers": 2,
      "off_": 1771924440000,
      "etr": null,
      "ticket": "24123628",
      "outageimpact": "Small",
      "outagetype": "Unplanned Outage",
      "medialink": null,
      "outagestatus": 0,
      "datastatus": null,
      "latlong": "4496301.049199998,-11728118.1744",
      "states": "CO",
      "crewstatus": null,
      "globalid": "{C349A0F0-4C4B-497C-8F69-22646B8F6B8B}",
      "county": "COSTILLA",
      "cause": "Outage",
      "city": "Fort Garland",
      "xcelarea": "Fort Garland"
    },
    "geometry": {
      "x": -11728118.1744,
      "y": 4496301.0491999984
    }
  },
  {
    "attributes": {
      "objectid": 89056,
      "boundary": null,
      "comments": "Crews are in the area working to restore power as quickly and safely as possible. Please continue to check back for estimated restoration time updates. Thank you for your patience.",
      "customers": 100,
      "off_": 1771924080000,
      "etr": 1771941600000,
      "ticket": "24123628",
      "outageimpact": "Medium",
      "outagetype": "Unplanned Outage",
      "medialink": null,
      "outagestatus": 0,
      "datastatus": null,
      "latlong": "4833869.1455999985,-11696250.892900001",
      "states": "CO",
      "crewstatus": "Crew Onsite",
      "globalid": "{5C2AB0BE-4CB9-4937-8925-B6C38C05C925}",
      "county": "JEFFERSON",
      "cause": "Outage",
      "city": "Wheat Ridge",
      "xcelarea": "Wheat Ridge"
    },
    "geometry": {
      "x": -11696250.892900001,
      "y": 4833869.1455999985
    }
  },
  {
    "attributes": {
      "objectid": 89086,
      "boundary": null,
      "comments": "Crews are working to restore power as quickly and safely as possible. Please continue to check back for estimated restoration time updates. Thank you for your patience.",
      "customers": 17,
      "off_": 1771925520000,
      "etr": 1771944300000,
      "ticket": "24123628",
      "outageimpact": "Small",
      "outagetype": "Unplanned Outage",
      "medialink": null,
      "outagestatus": 0,
      "datastatus": null,
      "latlong": "4655927.631300002,-11799612.3559",
      "states": "CO",
      "crewstatus": null,
      "globalid": "{A9A40BB3-A352-4BD5-B3F3-9D66CFF954A4}",
      "county": "CHAFFEE",
      "cause": "Outage",
      "city": "Salida",
      "xcelarea": "Salida"
    },
    "geometry": {
      "x": -11799612.355900001,
      "y": 4655927.6313000023
    }
  },
  {
    "attributes": {
      "objectid": 89096,
      "boundary": null,
      "comments": "Crews are working to restore power as quickly and safely as possible. Please continue to check back for estimated restoration time updates. Thank you for your patience.",
      "customers": 5,
      "off_": 1771926120000,
      "etr": 1771939800000,
      "ticket": "24123628",
      "outageimpact": "Small",
      "outagetype": "Unplanned Outage",
      "medialink": null,
      "outagestatus": 0,
      "datastatus": null,
      "latlong": "4826492.548199996,-11694330.8543",
      "states": "CO",
      "crewstatus": null,
      "globalid": "{58295332-C23B-4A55-BF53-D86B15A1B4EC}",
      "county": "DENVER",
      "cause": "Outage",
      "city": "Denver",
      "xcelarea": "Denver"
    },
    "geometry": {
      "x": -11694330.8543,
      "y": 4826492.5481999964
    }
  },
  {
    "attributes": {
      "objectid": 89036,
      "boundary": null,
      "comments": "Crews are working to restore power as quickly and safely as possible. Please continue to check back for estimated restoration time updates. Thank you for your patience.",
      "customers": 3,
      "off_": 1771923960000,
      "etr": null,
      "ticket": "24123628",
      "outageimpact": "Small",
      "outagetype": "Unplanned Outage",
      "medialink": null,
      "outagestatus": 0,
      "datastatus": null,
      "latlong": "4829137.4738000035,-11740042.6314",
      "states": "CO",
      "crewstatus": null,
      "globalid": "{57C5F857-7CDF-46B3-884A-48E82BAD9891}",
      "county": "CLEAR CREEK",
      "cause": "Outage",
      "city": "Idaho Springs",
      "xcelarea": "Idaho Springs"
    },
    "geometry": {
      "x": -11740042.6314,
      "y": 4829137.4738000035
    }
  },
  {
    "attributes": {
      "objectid": 88976,
      "boundary": null,
      "comments": "Crews are working to restore power as quickly and safely as possible. Please continue to check back for estimated restoration time updates. Thank you for your patience.",
      "customers": 3,
      "off_": 1771921620000,
      "etr": 1771971300000,
      "ticket": "24123628",
      "outageimpact": "Small",
      "outagetype": "Unplanned Outage",
      "medialink": null,
      "outagestatus": 0,
      "datastatus": null,
      "latlong": "4968636.710600004,-11664731.5594",
      "states": "CO",
      "crewstatus": null,
      "globalid": "{C381FF8D-0092-4EAB-B124-4C996E4237B4}",
      "county": "WELD",
      "cause": "Outage",
      "city": "Nunn",
      "xcelarea": "Nunn"
    },
    "geometry": {
      "x": -11664731.5594,
      "y": 4968636.7106000036
    }
  }
]
