[
  {
    "attributes": {
      "objectid": 69055,
      "boundary": null,
      "comments": "Crews are working to restore power as quickly and safely as possible. Please continue to check back for estimated restoration time updates. Thank you for your patience.",
      "customers": 9,
      "off_": 1769533620000,
      "etr": 1769562900000,
      "ticket": "28002933",
      "outageimpact": "Small",
      "outagetype": "Unplanned Outage",
      "medialink": null,
      "outagestatus": 0,
      "datastatus": null,
      "latlong": "4814361.5524,-11665969.0147",
      "states": "CO",
      "crewstatus": null,
      "globalid": "{EF48B9A0-5918-4FEB-B9C4-24900FD1FEB5}",
      "county": "ARAPAHOE",
      "cause": "Outage",
      "city": "Aurora",
      "xcelarea": "Aurora"
    },
    "geometry": {
      "x": -11665969.014699999,
      "y": 4814361.5524000004
    }
  },
  {
    "attributes": {
      "objectid": 69103,
      "boundary": null,
      "comments": "Crews are working to restore power as quickly and safely as possible. Please continue to check back for estimated restoration time updates. Thank you for your patience.",
      "customers": 5,
      "off_": 1769542740000,
      "etr": 1769567400000,
      "ticket": "28002933",
      "outageimpact": "Small",
      "outagetype": "Unplanned Outage",
      "medialink": null,
      "outagestatus": 0,
      "datastatus": null,
      "latlong": "4867847.5603,-11717660.396200001",
      "states": "CO",
      "crewstatus": null,
      "globalid": "{62680841-83A7-4A97-8A74-2EBE32B5937C}",
      "county": "BOULDER",
      "cause": "Outage",
      "city": "Boulder",
      "xcelarea": "Boulder"
    },
    "geometry": {
      "x": -11717660.396200001,
      "y": 4867847.5603
    }
  }
]
